.gitignore
.gitlab-ci.yml
CHANGELOG.md
Dockerfile
LICENSE
Makefile
README.rst
dev-requirements.txt
requirements.txt
setup.cfg
setup.py
tox.ini
src/gitlab_auto_mr/__init__.py
src/gitlab_auto_mr/cli.py
src/gitlab_auto_mr.egg-info/PKG-INFO
src/gitlab_auto_mr.egg-info/SOURCES.txt
src/gitlab_auto_mr.egg-info/dependency_links.txt
src/gitlab_auto_mr.egg-info/entry_points.txt
src/gitlab_auto_mr.egg-info/not-zip-safe
src/gitlab_auto_mr.egg-info/requires.txt
src/gitlab_auto_mr.egg-info/top_level.txt
tests/__init__.py
tests/conftest.py
tests/data/MR.md
tests/integration/__init__.py
tests/integration/test_integration.py
tests/unit/__init__.py
tests/unit/test_cli.py