Metadata-Version: 2.1
Name: gitlab-auto-mr
Version: 1.1.7
Summary: A simple tool for automatically creating merge requests in GitLab
Home-page: https://gitlab.com/gitlab-automation-toolkit/gitlab-auto-mr
Author: Haseeb Majid
Author-email: me@haseebmajid.com
License: Apache License
Keywords: Python
Classifier: Programming Language :: Python
Classifier: Intended Audience :: Developers
Classifier: Operating System :: OS Independent
Classifier: Topic :: Software Development :: Libraries :: Python Modules
Requires-Python: ~=3.6
License-File: LICENSE
